LICENSE
MANIFEST.in
README.md
setup.py
pymarkdownlint/__init__.py
pymarkdownlint/cli.py
pymarkdownlint/config.py
pymarkdownlint/filefinder.py
pymarkdownlint/lint.py
pymarkdownlint/options.py
pymarkdownlint/rules.py
pymarkdownlint.egg-info/PKG-INFO
pymarkdownlint.egg-info/SOURCES.txt
pymarkdownlint.egg-info/dependency_links.txt
pymarkdownlint.egg-info/entry_points.txt
pymarkdownlint.egg-info/pbr.json
pymarkdownlint.egg-info/requires.txt
pymarkdownlint.egg-info/top_level.txt