Metadata-Version: 1.1
Name: pymarkdownlint
Version: 0.3.1
Summary: Markdown linter written in python. Under active development.
Home-page: https://github.com/jorisroovers/pymarkdownlint
Author: Joris Roovers
Author-email: UNKNOWN
License: MIT
Keywords: markdown markdownlint pymarkdownlint
Platform: UNKNOWN
Classifier: Development Status :: 3 - Alpha
Classifier: Operating System :: OS Independent
Classifier: Programming Language :: Python
Classifier: Environment :: Console
Classifier: Intended Audience :: Developers
Classifier: License :: OSI Approved :: MIT License
